ladybug_dotnet/__init__.py
ladybug_dotnet/color.py
ladybug_dotnet/download.py
ladybug_dotnet-1.1.1.dist-info/LICENSE
ladybug_dotnet-1.1.1.dist-info/METADATA
ladybug_dotnet-1.1.1.dist-info/WHEEL
ladybug_dotnet-1.1.1.dist-info/top_level.txt
ladybug_dotnet-1.1.1.dist-info/RECORD
