Metadata-Version: 2.1
Name: ladybug-dotnet
Version: 1.1.1
Summary: A library for communicating between Ladybug Tools core Python libraries and .NET libraries
Home-page: https://github.com/ladybug-tools/ladybug-dotnet
Author: Ladybug Tools
Author-email: info@ladybug.tools
License: UNKNOWN
Platform: UNKNOWN
Classifier: Programming Language :: Python :: 2.7
Classifier: Programming Language :: Python :: 3.6
Classifier: Programming Language :: Python :: Implementation :: CPython
Classifier: License :: OSI Approved :: GNU General Public License v3 (GPLv3)
Classifier: Operating System :: OS Independent
